[
 {
  "builder_description": "Standard electrical cable baseline for the InductOne REV E electrical BOM.\n\nConfiguration effect:\nAll managed balloon callouts resolve to the standard BOM rows, and option/extension rows are pruned from the configurable electrical cable balloons.\n\nNotes:\nAlways applied as the single-member required baseline group and not independently deselectable. Every other DEV option layers on this baseline.",
  "deprecated_date": null,
  "docstatus": 0,
  "doctype": "InductOne Configuration Option",
  "effective_date": null,
  "internal_notes": "Use for the standard electrical cable configuration when no electrical panel or component relocation deviations are required.",
  "is_active": 1,
  "is_default_selection": 1,
  "mapping_status": "Complete",
  "mappings_table": [
   {
    "action": "REMOVE",
    "expand_mode": "AS_ITEM_ONLY",
    "parameter_key": null,
    "parent": "DEV-BASELINE",
    "parentfield": "mappings_table",
    "parenttype": "InductOne Configuration Option",
    "preserve_target_item_identity": 1,
    "qty_fixed": 1.0,
    "qty_source": "FIXED",
    "replace_count": 1,
    "replace_scope": "ALL_OCCURRENCES",
    "replace_with_bom": null,
    "replace_with_item": "",
    "required_for_release": 1,
    "row_order": 10,
    "structural_effect_mode": "SUPPRESS_TARGET_NODE",
    "target_balloon": "137",
    "target_bom": null,
    "target_item": "MCVP-19MFP-10M"
   },
   {
    "action": "REMOVE",
    "expand_mode": "AS_ITEM_ONLY",
    "parameter_key": null,
    "parent": "DEV-BASELINE",
    "parentfield": "mappings_table",
    "parenttype": "InductOne Configuration Option",
    "preserve_target_item_identity": 1,
    "qty_fixed": 1.0,
    "qty_source": "FIXED",
    "replace_count": 1,
    "replace_scope": "ALL_OCCURRENCES",
    "replace_with_bom": null,
    "replace_with_item": "",
    "required_for_release": 1,
    "row_order": 20,
    "structural_effect_mode": "SUPPRESS_TARGET_NODE",
    "target_balloon": "140",
    "target_bom": null,
    "target_item": "1407379"
   },
   {
    "action": "REMOVE",
    "expand_mode": "AS_ITEM_ONLY",
    "parameter_key": null,
    "parent": "DEV-BASELINE",
    "parentfield": "mappings_table",
    "parenttype": "InductOne Configuration Option",
    "preserve_target_item_identity": 1,
    "qty_fixed": 1.0,
    "qty_source": "FIXED",
    "replace_count": 1,
    "replace_scope": "ALL_OCCURRENCES",
    "replace_with_bom": null,
    "replace_with_item": "",
    "required_for_release": 1,
    "row_order": 30,
    "structural_effect_mode": "SUPPRESS_TARGET_NODE",
    "target_balloon": "141",
    "target_bom": null,
    "target_item": "1407486"
   },
   {
    "action": "REMOVE",
    "expand_mode": "AS_ITEM_ONLY",
    "parameter_key": null,
    "parent": "DEV-BASELINE",
    "parentfield": "mappings_table",
    "parenttype": "InductOne Configuration Option",
    "preserve_target_item_identity": 1,
    "qty_fixed": 1.0,
    "qty_source": "FIXED",
    "replace_count": 1,
    "replace_scope": "ALL_OCCURRENCES",
    "replace_with_bom": null,
    "replace_with_item": "",
    "required_for_release": 1,
    "row_order": 40,
    "structural_effect_mode": "SUPPRESS_TARGET_NODE",
    "target_balloon": "144",
    "target_bom": null,
    "target_item": "1407363"
   },
   {
    "action": "REMOVE",
    "expand_mode": "AS_ITEM_ONLY",
    "parameter_key": null,
    "parent": "DEV-BASELINE",
    "parentfield": "mappings_table",
    "parenttype": "InductOne Configuration Option",
    "preserve_target_item_identity": 1,
    "qty_fixed": 1.0,
    "qty_source": "FIXED",
    "replace_count": 1,
    "replace_scope": "ALL_OCCURRENCES",
    "replace_with_bom": null,
    "replace_with_item": "",
    "required_for_release": 1,
    "row_order": 50,
    "structural_effect_mode": "SUPPRESS_TARGET_NODE",
    "target_balloon": "154",
    "target_bom": null,
    "target_item": "1417892"
   },
   {
    "action": "REMOVE",
    "expand_mode": "AS_ITEM_ONLY",
    "parameter_key": null,
    "parent": "DEV-BASELINE",
    "parentfield": "mappings_table",
    "parenttype": "InductOne Configuration Option",
    "preserve_target_item_identity": 1,
    "qty_fixed": 1.0,
    "qty_source": "FIXED",
    "replace_count": 1,
    "replace_scope": "ALL_OCCURRENCES",
    "replace_with_bom": null,
    "replace_with_item": "",
    "required_for_release": 1,
    "row_order": 60,
    "structural_effect_mode": "SUPPRESS_TARGET_NODE",
    "target_balloon": "159",
    "target_bom": null,
    "target_item": "MDCM-8FP-10M-R  & MDC-8MP-FW11"
   },
   {
    "action": "REMOVE",
    "expand_mode": "AS_ITEM_ONLY",
    "parameter_key": null,
    "parent": "DEV-BASELINE",
    "parentfield": "mappings_table",
    "parenttype": "InductOne Configuration Option",
    "preserve_target_item_identity": 1,
    "qty_fixed": 1.0,
    "qty_source": "FIXED",
    "replace_count": 1,
    "replace_scope": "ALL_OCCURRENCES",
    "replace_with_bom": null,
    "replace_with_item": "",
    "required_for_release": 1,
    "row_order": 70,
    "structural_effect_mode": "SUPPRESS_TARGET_NODE",
    "target_balloon": "172",
    "target_bom": null,
    "target_item": "11283"
   },
   {
    "action": "REMOVE",
    "expand_mode": "AS_ITEM_ONLY",
    "parameter_key": null,
    "parent": "DEV-BASELINE",
    "parentfield": "mappings_table",
    "parenttype": "InductOne Configuration Option",
    "preserve_target_item_identity": 1,
    "qty_fixed": 1.0,
    "qty_source": "FIXED",
    "replace_count": 1,
    "replace_scope": "ALL_OCCURRENCES",
    "replace_with_bom": null,
    "replace_with_item": "",
    "required_for_release": 1,
    "row_order": 80,
    "structural_effect_mode": "SUPPRESS_TARGET_NODE",
    "target_balloon": "173",
    "target_bom": null,
    "target_item": "11351"
   },
   {
    "action": "REMOVE",
    "expand_mode": "AS_ITEM_ONLY",
    "parameter_key": null,
    "parent": "DEV-BASELINE",
    "parentfield": "mappings_table",
    "parenttype": "InductOne Configuration Option",
    "preserve_target_item_identity": 1,
    "qty_fixed": 1.0,
    "qty_source": "FIXED",
    "replace_count": 1,
    "replace_scope": "ALL_OCCURRENCES",
    "replace_with_bom": null,
    "replace_with_item": "",
    "required_for_release": 1,
    "row_order": 90,
    "structural_effect_mode": "SUPPRESS_TARGET_NODE",
    "target_balloon": "190",
    "target_bom": null,
    "target_item": "1291280"
   },
   {
    "action": "REMOVE",
    "expand_mode": "AS_ITEM_ONLY",
    "parameter_key": null,
    "parent": "DEV-BASELINE",
    "parentfield": "mappings_table",
    "parenttype": "InductOne Configuration Option",
    "preserve_target_item_identity": 1,
    "qty_fixed": 1.0,
    "qty_source": "FIXED",
    "replace_count": 1,
    "replace_scope": "ALL_OCCURRENCES",
    "replace_with_bom": null,
    "replace_with_item": "",
    "required_for_release": 1,
    "row_order": 100,
    "structural_effect_mode": "SUPPRESS_TARGET_NODE",
    "target_balloon": "191",
    "target_bom": null,
    "target_item": "1000517"
   },
   {
    "action": "REMOVE",
    "expand_mode": "AS_ITEM_ONLY",
    "parameter_key": null,
    "parent": "DEV-BASELINE",
    "parentfield": "mappings_table",
    "parenttype": "InductOne Configuration Option",
    "preserve_target_item_identity": 1,
    "qty_fixed": 1.0,
    "qty_source": "FIXED",
    "replace_count": 1,
    "replace_scope": "ALL_OCCURRENCES",
    "replace_with_bom": null,
    "replace_with_item": "",
    "required_for_release": 1,
    "row_order": 110,
    "structural_effect_mode": "SUPPRESS_TARGET_NODE",
    "target_balloon": "193",
    "target_bom": null,
    "target_item": "1417903"
   },
   {
    "action": "REMOVE",
    "expand_mode": "AS_ITEM_ONLY",
    "parameter_key": null,
    "parent": "DEV-BASELINE",
    "parentfield": "mappings_table",
    "parenttype": "InductOne Configuration Option",
    "preserve_target_item_identity": 1,
    "qty_fixed": 1.0,
    "qty_source": "FIXED",
    "replace_count": 1,
    "replace_scope": "ALL_OCCURRENCES",
    "replace_with_bom": null,
    "replace_with_item": "",
    "required_for_release": 1,
    "row_order": 120,
    "structural_effect_mode": "SUPPRESS_TARGET_NODE",
    "target_balloon": "143",
    "target_bom": null,
    "target_item": "1407402"
   },
   {
    "action": "REMOVE",
    "expand_mode": "AS_ITEM_ONLY",
    "parameter_key": null,
    "parent": "DEV-BASELINE",
    "parentfield": "mappings_table",
    "parenttype": "InductOne Configuration Option",
    "preserve_target_item_identity": 1,
    "qty_fixed": 1.0,
    "qty_source": "FIXED",
    "replace_count": 1,
    "replace_scope": "ALL_OCCURRENCES",
    "replace_with_bom": null,
    "replace_with_item": "",
    "required_for_release": 1,
    "row_order": 130,
    "structural_effect_mode": "SUPPRESS_TARGET_NODE",
    "target_balloon": "145",
    "target_bom": null,
    "target_item": "MCVP-12MMFP-5M"
   },
   {
    "action": "REMOVE",
    "expand_mode": "AS_ITEM_ONLY",
    "parameter_key": null,
    "parent": "DEV-BASELINE",
    "parentfield": "mappings_table",
    "parenttype": "InductOne Configuration Option",
    "preserve_target_item_identity": 1,
    "qty_fixed": 1.0,
    "qty_source": "FIXED",
    "replace_count": 1,
    "replace_scope": "ALL_OCCURRENCES",
    "replace_with_bom": null,
    "replace_with_item": "",
    "required_for_release": 1,
    "row_order": 140,
    "structural_effect_mode": "SUPPRESS_TARGET_NODE",
    "target_balloon": "149",
    "target_bom": null,
    "target_item": "1276573"
   },
   {
    "action": "REMOVE",
    "expand_mode": "AS_ITEM_ONLY",
    "parameter_key": null,
    "parent": "DEV-BASELINE",
    "parentfield": "mappings_table",
    "parenttype": "InductOne Configuration Option",
    "preserve_target_item_identity": 1,
    "qty_fixed": 1.0,
    "qty_source": "FIXED",
    "replace_count": 1,
    "replace_scope": "ALL_OCCURRENCES",
    "replace_with_bom": null,
    "replace_with_item": "",
    "required_for_release": 1,
    "row_order": 150,
    "structural_effect_mode": "SUPPRESS_TARGET_NODE",
    "target_balloon": "156",
    "target_bom": null,
    "target_item": "RSM RKM 30-5M/S101"
   }
  ],
  "modified": "2026-07-08 00:21:43.736158",
  "name": "DEV-BASELINE",
  "option_category": "Electrical",
  "option_code": "DEV-BASELINE",
  "option_group": "Electrical Cable Baseline",
  "option_group_required": 1,
  "option_name": "Deviation — All Standard (Baseline)",
  "owner_role": "Ops",
  "requires_ops_approval": 0,
  "sort_order": 10,
  "status": "Draft",
  "workflow_state": null
 },
 {
  "builder_description": "MCP panel remains in the standard location.\n\nConfiguration effect:\nNo change. Baseline standard cabling applies.\n\nNotes:\nDefault selection for this required option group. Mutually exclusive with the paired relocated option.",
  "deprecated_date": null,
  "docstatus": 0,
  "doctype": "InductOne Configuration Option",
  "effective_date": null,
  "internal_notes": "Use when the MCP panel remains in its standard location. Select the paired relocated option only when the MCP panel is moved from standard.",
  "is_active": 1,
  "is_default_selection": 1,
  "mapping_status": "Complete",
  "mappings_table": [],
  "modified": "2026-07-08 00:21:43.914920",
  "name": "DEV-PANEL-MCP-STD",
  "option_category": "Electrical",
  "option_code": "DEV-PANEL-MCP-STD",
  "option_group": "MCP Panel Position",
  "option_group_required": 1,
  "option_name": "MCP Panel — Standard",
  "owner_role": "Ops",
  "requires_ops_approval": 0,
  "sort_order": 20,
  "status": "Draft",
  "workflow_state": null
 },
 {
  "builder_description": "MCP panel relocated from the standard electrical layout.\n\nConfiguration effect:\nAdds extension rows: balloon 143 -> 1407402 (M12 D-CODE 5M extension); balloon 145 -> MCVP-12MMFP-5M (M23 12-pole 5M); balloon 149 -> 1276573 (M12 L-CODE 5M); balloon 156 -> RSM RKM 30-5M/S101 (7/8 in 3-pin 5M). No standard-row substitutions are made by this option.\n\nNotes:\nPaired with the standard option in the same required group; select only one. If this overlaps with the IPC panel relocation or a component relocation, the balloon-scoped resolver applies the same moved row once and prevents double cabling.",
  "deprecated_date": null,
  "docstatus": 0,
  "doctype": "InductOne Configuration Option",
  "effective_date": null,
  "internal_notes": "Use when the MCP panel is relocated and the standard cable set needs the relocation extension cabling.",
  "is_active": 1,
  "is_default_selection": 0,
  "mapping_status": "Complete",
  "mappings_table": [
   {
    "action": "ADD",
    "expand_mode": "AS_ITEM_ONLY",
    "parameter_key": null,
    "parent": "DEV-PANEL-MCP",
    "parentfield": "mappings_table",
    "parenttype": "InductOne Configuration Option",
    "preserve_target_item_identity": 1,
    "qty_fixed": 1.0,
    "qty_source": "FIXED",
    "replace_count": 1,
    "replace_scope": "ALL_OCCURRENCES",
    "replace_with_bom": null,
    "replace_with_item": "",
    "required_for_release": 1,
    "row_order": 10,
    "structural_effect_mode": "ADD_BRANCH",
    "target_balloon": "143",
    "target_bom": null,
    "target_item": "1407402"
   },
   {
    "action": "ADD",
    "expand_mode": "AS_ITEM_ONLY",
    "parameter_key": null,
    "parent": "DEV-PANEL-MCP",
    "parentfield": "mappings_table",
    "parenttype": "InductOne Configuration Option",
    "preserve_target_item_identity": 1,
    "qty_fixed": 1.0,
    "qty_source": "FIXED",
    "replace_count": 1,
    "replace_scope": "ALL_OCCURRENCES",
    "replace_with_bom": null,
    "replace_with_item": "",
    "required_for_release": 1,
    "row_order": 20,
    "structural_effect_mode": "ADD_BRANCH",
    "target_balloon": "145",
    "target_bom": null,
    "target_item": "MCVP-12MMFP-5M"
   },
   {
    "action": "ADD",
    "expand_mode": "AS_ITEM_ONLY",
    "parameter_key": null,
    "parent": "DEV-PANEL-MCP",
    "parentfield": "mappings_table",
    "parenttype": "InductOne Configuration Option",
    "preserve_target_item_identity": 1,
    "qty_fixed": 1.0,
    "qty_source": "FIXED",
    "replace_count": 1,
    "replace_scope": "ALL_OCCURRENCES",
    "replace_with_bom": null,
    "replace_with_item": "",
    "required_for_release": 1,
    "row_order": 30,
    "structural_effect_mode": "ADD_BRANCH",
    "target_balloon": "149",
    "target_bom": null,
    "target_item": "1276573"
   },
   {
    "action": "ADD",
    "expand_mode": "AS_ITEM_ONLY",
    "parameter_key": null,
    "parent": "DEV-PANEL-MCP",
    "parentfield": "mappings_table",
    "parenttype": "InductOne Configuration Option",
    "preserve_target_item_identity": 1,
    "qty_fixed": 1.0,
    "qty_source": "FIXED",
    "replace_count": 1,
    "replace_scope": "ALL_OCCURRENCES",
    "replace_with_bom": null,
    "replace_with_item": "",
    "required_for_release": 1,
    "row_order": 40,
    "structural_effect_mode": "ADD_BRANCH",
    "target_balloon": "156",
    "target_bom": null,
    "target_item": "RSM RKM 30-5M/S101"
   }
  ],
  "modified": "2026-07-08 00:21:43.936673",
  "name": "DEV-PANEL-MCP",
  "option_category": "Electrical",
  "option_code": "DEV-PANEL-MCP",
  "option_group": "MCP Panel Position",
  "option_group_required": 1,
  "option_name": "Deviation — MCP Panel Relocated",
  "owner_role": "Ops",
  "requires_ops_approval": 0,
  "sort_order": 30,
  "status": "Draft",
  "workflow_state": null
 },
 {
  "builder_description": "IPC panel remains in the standard location.\n\nConfiguration effect:\nNo change. Baseline standard cabling applies.\n\nNotes:\nDefault selection for this required option group. Mutually exclusive with the paired relocated option.",
  "deprecated_date": null,
  "docstatus": 0,
  "doctype": "InductOne Configuration Option",
  "effective_date": null,
  "internal_notes": "Use when the IPC panel remains in its standard location. Select the paired relocated option only when the IPC panel is moved from standard.",
  "is_active": 1,
  "is_default_selection": 1,
  "mapping_status": "Complete",
  "mappings_table": [],
  "modified": "2026-07-08 00:21:43.959029",
  "name": "DEV-PANEL-IPC-STD",
  "option_category": "Electrical",
  "option_code": "DEV-PANEL-IPC-STD",
  "option_group": "IPC Panel Position",
  "option_group_required": 1,
  "option_name": "IPC Panel — Standard",
  "owner_role": "Ops",
  "requires_ops_approval": 0,
  "sort_order": 40,
  "status": "Draft",
  "workflow_state": null
 },
 {
  "builder_description": "IPC panel relocated from the standard electrical layout.\n\nConfiguration effect:\nReplaces balloon 137 with MCVP-19MFP-10M x2 (M23 x19 10M); balloon 140 with 1407379 (M12 D-CODE 10M); balloon 141 with 1407486 (M12 X-CODE 10M); balloon 144 with 1407363 (RJ45-M12 D 10M); balloon 154 with 1417892 (M12 A 4-pin 10M); balloon 159 with MDCM-8FP-10M-R  & MDC-8MP-FW11 x2 (M12 8-pin 10M combined item); balloon 172 with 11283 x3 (RJ45 6M); balloon 173 with 11351 x2 (RJ45 15M); balloon 190 with 1291280 (M12 L 10M); balloon 191 with 1000517 x4 (USB-A 10M extension plus 1M locking lead); balloon 193 with 1417903 (M12 A 5-pin 10M). Adds extension rows: balloon 145 -> MCVP-12MMFP-5M and balloon 156 -> RSM RKM 30-5M/S101.\n\nNotes:\nPaired with the standard option in the same required group; select only one. If this overlaps with the IPC panel relocation or a component relocation, the balloon-scoped resolver applies the same moved row once and prevents double cabling.",
  "deprecated_date": null,
  "docstatus": 0,
  "doctype": "InductOne Configuration Option",
  "effective_date": null,
  "internal_notes": "Use when the IPC panel is relocated and the electrical cable package needs the longer relocated-panel cable set.",
  "is_active": 1,
  "is_default_selection": 0,
  "mapping_status": "Complete",
  "mappings_table": [
   {
    "action": "REPLACE",
    "expand_mode": "AS_ITEM_ONLY",
    "parameter_key": null,
    "parent": "DEV-PANEL-IPC",
    "parentfield": "mappings_table",
    "parenttype": "InductOne Configuration Option",
    "preserve_target_item_identity": 1,
    "qty_fixed": 1.0,
    "qty_source": "FIXED",
    "replace_count": 1,
    "replace_scope": "ALL_OCCURRENCES",
    "replace_with_bom": null,
    "replace_with_item": "MCVP-19MFP-10M",
    "required_for_release": 1,
    "row_order": 10,
    "structural_effect_mode": "AUTO",
    "target_balloon": "137",
    "target_bom": null,
    "target_item": "MCVP-19MFP-5M"
   },
   {
    "action": "REPLACE",
    "expand_mode": "AS_ITEM_ONLY",
    "parameter_key": null,
    "parent": "DEV-PANEL-IPC",
    "parentfield": "mappings_table",
    "parenttype": "InductOne Configuration Option",
    "preserve_target_item_identity": 1,
    "qty_fixed": 1.0,
    "qty_source": "FIXED",
    "replace_count": 1,
    "replace_scope": "ALL_OCCURRENCES",
    "replace_with_bom": null,
    "replace_with_item": "1407379",
    "required_for_release": 1,
    "row_order": 20,
    "structural_effect_mode": "AUTO",
    "target_balloon": "140",
    "target_bom": null,
    "target_item": "1407378"
   },
   {
    "action": "REPLACE",
    "expand_mode": "AS_ITEM_ONLY",
    "parameter_key": null,
    "parent": "DEV-PANEL-IPC",
    "parentfield": "mappings_table",
    "parenttype": "InductOne Configuration Option",
    "preserve_target_item_identity": 1,
    "qty_fixed": 1.0,
    "qty_source": "FIXED",
    "replace_count": 1,
    "replace_scope": "ALL_OCCURRENCES",
    "replace_with_bom": null,
    "replace_with_item": "1407486",
    "required_for_release": 1,
    "row_order": 30,
    "structural_effect_mode": "AUTO",
    "target_balloon": "141",
    "target_bom": null,
    "target_item": "1407485"
   },
   {
    "action": "REPLACE",
    "expand_mode": "AS_ITEM_ONLY",
    "parameter_key": null,
    "parent": "DEV-PANEL-IPC",
    "parentfield": "mappings_table",
    "parenttype": "InductOne Configuration Option",
    "preserve_target_item_identity": 1,
    "qty_fixed": 1.0,
    "qty_source": "FIXED",
    "replace_count": 1,
    "replace_scope": "ALL_OCCURRENCES",
    "replace_with_bom": null,
    "replace_with_item": "1407363",
    "required_for_release": 1,
    "row_order": 40,
    "structural_effect_mode": "AUTO",
    "target_balloon": "144",
    "target_bom": null,
    "target_item": "1407362"
   },
   {
    "action": "REPLACE",
    "expand_mode": "AS_ITEM_ONLY",
    "parameter_key": null,
    "parent": "DEV-PANEL-IPC",
    "parentfield": "mappings_table",
    "parenttype": "InductOne Configuration Option",
    "preserve_target_item_identity": 1,
    "qty_fixed": 1.0,
    "qty_source": "FIXED",
    "replace_count": 1,
    "replace_scope": "ALL_OCCURRENCES",
    "replace_with_bom": null,
    "replace_with_item": "1417892",
    "required_for_release": 1,
    "row_order": 50,
    "structural_effect_mode": "AUTO",
    "target_balloon": "154",
    "target_bom": null,
    "target_item": "1417891"
   },
   {
    "action": "REPLACE",
    "expand_mode": "AS_ITEM_ONLY",
    "parameter_key": null,
    "parent": "DEV-PANEL-IPC",
    "parentfield": "mappings_table",
    "parenttype": "InductOne Configuration Option",
    "preserve_target_item_identity": 1,
    "qty_fixed": 1.0,
    "qty_source": "FIXED",
    "replace_count": 1,
    "replace_scope": "ALL_OCCURRENCES",
    "replace_with_bom": null,
    "replace_with_item": "MDCM-8FP-10M-R  & MDC-8MP-FW11",
    "required_for_release": 1,
    "row_order": 60,
    "structural_effect_mode": "AUTO",
    "target_balloon": "159",
    "target_bom": null,
    "target_item": "WKC 8T-4-RSC 8T"
   },
   {
    "action": "REPLACE",
    "expand_mode": "AS_ITEM_ONLY",
    "parameter_key": null,
    "parent": "DEV-PANEL-IPC",
    "parentfield": "mappings_table",
    "parenttype": "InductOne Configuration Option",
    "preserve_target_item_identity": 1,
    "qty_fixed": 1.0,
    "qty_source": "FIXED",
    "replace_count": 1,
    "replace_scope": "ALL_OCCURRENCES",
    "replace_with_bom": null,
    "replace_with_item": "11283",
    "required_for_release": 1,
    "row_order": 70,
    "structural_effect_mode": "AUTO",
    "target_balloon": "172",
    "target_bom": null,
    "target_item": "11245"
   },
   {
    "action": "REPLACE",
    "expand_mode": "AS_ITEM_ONLY",
    "parameter_key": null,
    "parent": "DEV-PANEL-IPC",
    "parentfield": "mappings_table",
    "parenttype": "InductOne Configuration Option",
    "preserve_target_item_identity": 1,
    "qty_fixed": 1.0,
    "qty_source": "FIXED",
    "replace_count": 1,
    "replace_scope": "ALL_OCCURRENCES",
    "replace_with_bom": null,
    "replace_with_item": "11351",
    "required_for_release": 1,
    "row_order": 80,
    "structural_effect_mode": "AUTO",
    "target_balloon": "173",
    "target_bom": null,
    "target_item": "11283"
   },
   {
    "action": "REPLACE",
    "expand_mode": "AS_ITEM_ONLY",
    "parameter_key": null,
    "parent": "DEV-PANEL-IPC",
    "parentfield": "mappings_table",
    "parenttype": "InductOne Configuration Option",
    "preserve_target_item_identity": 1,
    "qty_fixed": 1.0,
    "qty_source": "FIXED",
    "replace_count": 1,
    "replace_scope": "ALL_OCCURRENCES",
    "replace_with_bom": null,
    "replace_with_item": "1291280",
    "required_for_release": 1,
    "row_order": 90,
    "structural_effect_mode": "AUTO",
    "target_balloon": "190",
    "target_bom": null,
    "target_item": "1425016"
   },
   {
    "action": "REPLACE",
    "expand_mode": "AS_ITEM_ONLY",
    "parameter_key": null,
    "parent": "DEV-PANEL-IPC",
    "parentfield": "mappings_table",
    "parenttype": "InductOne Configuration Option",
    "preserve_target_item_identity": 1,
    "qty_fixed": 1.0,
    "qty_source": "FIXED",
    "replace_count": 1,
    "replace_scope": "ALL_OCCURRENCES",
    "replace_with_bom": null,
    "replace_with_item": "1000517",
    "required_for_release": 1,
    "row_order": 100,
    "structural_effect_mode": "AUTO",
    "target_balloon": "191",
    "target_bom": null,
    "target_item": "1007-300-0002-02"
   },
   {
    "action": "REPLACE",
    "expand_mode": "AS_ITEM_ONLY",
    "parameter_key": null,
    "parent": "DEV-PANEL-IPC",
    "parentfield": "mappings_table",
    "parenttype": "InductOne Configuration Option",
    "preserve_target_item_identity": 1,
    "qty_fixed": 1.0,
    "qty_source": "FIXED",
    "replace_count": 1,
    "replace_scope": "ALL_OCCURRENCES",
    "replace_with_bom": null,
    "replace_with_item": "1417903",
    "required_for_release": 1,
    "row_order": 110,
    "structural_effect_mode": "AUTO",
    "target_balloon": "193",
    "target_bom": null,
    "target_item": "1417902"
   },
   {
    "action": "ADD",
    "expand_mode": "AS_ITEM_ONLY",
    "parameter_key": null,
    "parent": "DEV-PANEL-IPC",
    "parentfield": "mappings_table",
    "parenttype": "InductOne Configuration Option",
    "preserve_target_item_identity": 1,
    "qty_fixed": 1.0,
    "qty_source": "FIXED",
    "replace_count": 1,
    "replace_scope": "ALL_OCCURRENCES",
    "replace_with_bom": null,
    "replace_with_item": "",
    "required_for_release": 1,
    "row_order": 120,
    "structural_effect_mode": "ADD_BRANCH",
    "target_balloon": "145",
    "target_bom": null,
    "target_item": "MCVP-12MMFP-5M"
   },
   {
    "action": "ADD",
    "expand_mode": "AS_ITEM_ONLY",
    "parameter_key": null,
    "parent": "DEV-PANEL-IPC",
    "parentfield": "mappings_table",
    "parenttype": "InductOne Configuration Option",
    "preserve_target_item_identity": 1,
    "qty_fixed": 1.0,
    "qty_source": "FIXED",
    "replace_count": 1,
    "replace_scope": "ALL_OCCURRENCES",
    "replace_with_bom": null,
    "replace_with_item": "",
    "required_for_release": 1,
    "row_order": 130,
    "structural_effect_mode": "ADD_BRANCH",
    "target_balloon": "156",
    "target_bom": null,
    "target_item": "RSM RKM 30-5M/S101"
   }
  ],
  "modified": "2026-07-08 00:21:43.972633",
  "name": "DEV-PANEL-IPC",
  "option_category": "Electrical",
  "option_code": "DEV-PANEL-IPC",
  "option_group": "IPC Panel Position",
  "option_group_required": 1,
  "option_name": "Deviation — IPC Panel Relocated",
  "owner_role": "Ops",
  "requires_ops_approval": 0,
  "sort_order": 50,
  "status": "Draft",
  "workflow_state": null
 },
 {
  "builder_description": "HMI remains in the standard location.\n\nConfiguration effect:\nNo change. Baseline standard cabling applies.\n\nNotes:\nDefault selection for this required option group. Mutually exclusive with the paired relocated option.",
  "deprecated_date": null,
  "docstatus": 0,
  "doctype": "InductOne Configuration Option",
  "effective_date": null,
  "internal_notes": "Use when the HMI remains in its standard location. Select the paired relocated option only when the HMI is moved from standard.",
  "is_active": 1,
  "is_default_selection": 1,
  "mapping_status": "Complete",
  "mappings_table": [],
  "modified": "2026-07-08 00:21:44.022927",
  "name": "DEV-COMP-HMI-STD",
  "option_category": "Electrical",
  "option_code": "DEV-COMP-HMI-STD",
  "option_group": "HMI Position",
  "option_group_required": 1,
  "option_name": "HMI — Standard",
  "owner_role": "Ops",
  "requires_ops_approval": 0,
  "sort_order": 60,
  "status": "Draft",
  "workflow_state": null
 },
 {
  "builder_description": "HMI relocated from the standard electrical layout.\n\nConfiguration effect:\nReplaces balloon 140 with 1407379 (M12 D-CODE 10M); balloon 141 with 1407486 (M12 X-CODE 10M); balloon 154 with 1417892 (M12 A 4-pin 10M). No other managed balloons are changed by this option.\n\nNotes:\nPaired with the standard option in the same required group; select only one. If this overlaps with the IPC panel relocation or a component relocation, the balloon-scoped resolver applies the same moved row once and prevents double cabling.",
  "deprecated_date": null,
  "docstatus": 0,
  "doctype": "InductOne Configuration Option",
  "effective_date": null,
  "internal_notes": "Use when the HMI is relocated and only the HMI-related electrical cables need the relocated lengths.",
  "is_active": 1,
  "is_default_selection": 0,
  "mapping_status": "Complete",
  "mappings_table": [
   {
    "action": "REPLACE",
    "expand_mode": "AS_ITEM_ONLY",
    "parameter_key": null,
    "parent": "DEV-COMP-HMI",
    "parentfield": "mappings_table",
    "parenttype": "InductOne Configuration Option",
    "preserve_target_item_identity": 1,
    "qty_fixed": 1.0,
    "qty_source": "FIXED",
    "replace_count": 1,
    "replace_scope": "ALL_OCCURRENCES",
    "replace_with_bom": null,
    "replace_with_item": "1407379",
    "required_for_release": 1,
    "row_order": 10,
    "structural_effect_mode": "AUTO",
    "target_balloon": "140",
    "target_bom": null,
    "target_item": "1407378"
   },
   {
    "action": "REPLACE",
    "expand_mode": "AS_ITEM_ONLY",
    "parameter_key": null,
    "parent": "DEV-COMP-HMI",
    "parentfield": "mappings_table",
    "parenttype": "InductOne Configuration Option",
    "preserve_target_item_identity": 1,
    "qty_fixed": 1.0,
    "qty_source": "FIXED",
    "replace_count": 1,
    "replace_scope": "ALL_OCCURRENCES",
    "replace_with_bom": null,
    "replace_with_item": "1407486",
    "required_for_release": 1,
    "row_order": 20,
    "structural_effect_mode": "AUTO",
    "target_balloon": "141",
    "target_bom": null,
    "target_item": "1407485"
   },
   {
    "action": "REPLACE",
    "expand_mode": "AS_ITEM_ONLY",
    "parameter_key": null,
    "parent": "DEV-COMP-HMI",
    "parentfield": "mappings_table",
    "parenttype": "InductOne Configuration Option",
    "preserve_target_item_identity": 1,
    "qty_fixed": 1.0,
    "qty_source": "FIXED",
    "replace_count": 1,
    "replace_scope": "ALL_OCCURRENCES",
    "replace_with_bom": null,
    "replace_with_item": "1417892",
    "required_for_release": 1,
    "row_order": 30,
    "structural_effect_mode": "AUTO",
    "target_balloon": "154",
    "target_bom": null,
    "target_item": "1417891"
   }
  ],
  "modified": "2026-07-08 00:21:44.038650",
  "name": "DEV-COMP-HMI",
  "option_category": "Electrical",
  "option_code": "DEV-COMP-HMI",
  "option_group": "HMI Position",
  "option_group_required": 1,
  "option_name": "Deviation — HMI Relocated",
  "owner_role": "Ops",
  "requires_ops_approval": 0,
  "sort_order": 70,
  "status": "Draft",
  "workflow_state": null
 },
 {
  "builder_description": "Stacklight remains in the standard location.\n\nConfiguration effect:\nNo change. Baseline standard cabling applies.\n\nNotes:\nDefault selection for this required option group. Mutually exclusive with the paired relocated option.",
  "deprecated_date": null,
  "docstatus": 0,
  "doctype": "InductOne Configuration Option",
  "effective_date": null,
  "internal_notes": "Use when the stacklight remains in its standard location. Select the paired relocated option only when the stacklight is moved from standard.",
  "is_active": 1,
  "is_default_selection": 1,
  "mapping_status": "Complete",
  "mappings_table": [],
  "modified": "2026-07-08 00:21:44.059212",
  "name": "DEV-COMP-STACK-STD",
  "option_category": "Electrical",
  "option_code": "DEV-COMP-STACK-STD",
  "option_group": "Stacklight Position",
  "option_group_required": 1,
  "option_name": "Stacklight — Standard",
  "owner_role": "Ops",
  "requires_ops_approval": 0,
  "sort_order": 80,
  "status": "Draft",
  "workflow_state": null
 },
 {
  "builder_description": "Stacklight relocated from the standard electrical layout.\n\nConfiguration effect:\nReplaces balloon 193 with 1417903 (M12 A 5-pin 10M). No other managed balloons are changed by this option.\n\nNotes:\nPaired with the standard option in the same required group; select only one. If this overlaps with the IPC panel relocation or a component relocation, the balloon-scoped resolver applies the same moved row once and prevents double cabling.",
  "deprecated_date": null,
  "docstatus": 0,
  "doctype": "InductOne Configuration Option",
  "effective_date": null,
  "internal_notes": "Use when the stacklight is relocated and only the stacklight electrical cable needs the relocated length.",
  "is_active": 1,
  "is_default_selection": 0,
  "mapping_status": "Complete",
  "mappings_table": [
   {
    "action": "REPLACE",
    "expand_mode": "AS_ITEM_ONLY",
    "parameter_key": null,
    "parent": "DEV-COMP-STACK",
    "parentfield": "mappings_table",
    "parenttype": "InductOne Configuration Option",
    "preserve_target_item_identity": 1,
    "qty_fixed": 1.0,
    "qty_source": "FIXED",
    "replace_count": 1,
    "replace_scope": "ALL_OCCURRENCES",
    "replace_with_bom": null,
    "replace_with_item": "1417903",
    "required_for_release": 1,
    "row_order": 10,
    "structural_effect_mode": "AUTO",
    "target_balloon": "193",
    "target_bom": null,
    "target_item": "1417902"
   }
  ],
  "modified": "2026-07-08 00:21:44.073612",
  "name": "DEV-COMP-STACK",
  "option_category": "Electrical",
  "option_code": "DEV-COMP-STACK",
  "option_group": "Stacklight Position",
  "option_group_required": 1,
  "option_name": "Deviation — Stacklight Relocated",
  "owner_role": "Ops",
  "requires_ops_approval": 0,
  "sort_order": 90,
  "status": "Draft",
  "workflow_state": null
 },
 {
  "builder_description": "Fortress safety component remains in the standard location.\n\nConfiguration effect:\nNo change. Baseline standard cabling applies.\n\nNotes:\nDefault selection for this required option group. Mutually exclusive with the paired relocated option.",
  "deprecated_date": null,
  "docstatus": 0,
  "doctype": "InductOne Configuration Option",
  "effective_date": null,
  "internal_notes": "Use when the Fortress safety component remains in its standard location. Select the paired relocated option only when Fortress is moved from standard.",
  "is_active": 1,
  "is_default_selection": 1,
  "mapping_status": "Complete",
  "mappings_table": [],
  "modified": "2026-07-08 00:21:44.100443",
  "name": "DEV-COMP-FORTRESS-STD",
  "option_category": "Electrical",
  "option_code": "DEV-COMP-FORTRESS-STD",
  "option_group": "Fortress Position",
  "option_group_required": 1,
  "option_name": "Fortress — Standard",
  "owner_role": "Ops",
  "requires_ops_approval": 0,
  "sort_order": 100,
  "status": "Draft",
  "workflow_state": null
 },
 {
  "builder_description": "Fortress safety component relocated from the standard electrical layout.\n\nConfiguration effect:\nReplaces balloon 137 with MCVP-19MFP-10M x2 (M23 x19 10M). No other managed balloons are changed by this option.\n\nNotes:\nPaired with the standard option in the same required group; select only one. If this overlaps with the IPC panel relocation or a component relocation, the balloon-scoped resolver applies the same moved row once and prevents double cabling.",
  "deprecated_date": null,
  "docstatus": 0,
  "doctype": "InductOne Configuration Option",
  "effective_date": null,
  "internal_notes": "Use when Fortress is relocated and only the Fortress electrical cable needs the relocated length.",
  "is_active": 1,
  "is_default_selection": 0,
  "mapping_status": "Complete",
  "mappings_table": [
   {
    "action": "REPLACE",
    "expand_mode": "AS_ITEM_ONLY",
    "parameter_key": null,
    "parent": "DEV-COMP-FORTRESS",
    "parentfield": "mappings_table",
    "parenttype": "InductOne Configuration Option",
    "preserve_target_item_identity": 1,
    "qty_fixed": 1.0,
    "qty_source": "FIXED",
    "replace_count": 1,
    "replace_scope": "ALL_OCCURRENCES",
    "replace_with_bom": null,
    "replace_with_item": "MCVP-19MFP-10M",
    "required_for_release": 1,
    "row_order": 10,
    "structural_effect_mode": "AUTO",
    "target_balloon": "137",
    "target_bom": null,
    "target_item": "MCVP-19MFP-5M"
   }
  ],
  "modified": "2026-07-08 00:21:44.121465",
  "name": "DEV-COMP-FORTRESS",
  "option_category": "Electrical",
  "option_code": "DEV-COMP-FORTRESS",
  "option_group": "Fortress Position",
  "option_group_required": 1,
  "option_name": "Deviation — Fortress Relocated",
  "owner_role": "Ops",
  "requires_ops_approval": 0,
  "sort_order": 110,
  "status": "Draft",
  "workflow_state": null
 },
 {
  "builder_description": "Magnet lock remains in the standard location.\n\nConfiguration effect:\nNo change. Baseline standard cabling applies.\n\nNotes:\nDefault selection for this required option group. Mutually exclusive with the paired relocated option.",
  "deprecated_date": null,
  "docstatus": 0,
  "doctype": "InductOne Configuration Option",
  "effective_date": null,
  "internal_notes": "Use when the magnet lock remains in its standard location. Select the paired relocated option only when the magnet lock is moved from standard.",
  "is_active": 1,
  "is_default_selection": 1,
  "mapping_status": "Complete",
  "mappings_table": [],
  "modified": "2026-07-08 11:04:13.735241",
  "name": "DEV-COMP-MAGLOCK-STD",
  "option_category": "Electrical",
  "option_code": "DEV-COMP-MAGLOCK-STD",
  "option_group": "Maglock Position",
  "option_group_required": 1,
  "option_name": "Magnet Lock — Standard",
  "owner_role": "Ops",
  "requires_ops_approval": 0,
  "sort_order": 120,
  "status": "Draft",
  "workflow_state": null
 },
 {
  "builder_description": "Magnet lock relocated from the standard electrical layout.\n\nConfiguration effect:\nReplaces balloon 159 with MDCM-8FP-10M-R  & MDC-8MP-FW11 x2 (M12 8-pin 10M combined item). No other managed balloons are changed by this option.\n\nNotes:\nPaired with the standard option in the same required group; select only one. If this overlaps with the IPC panel relocation or a component relocation, the balloon-scoped resolver applies the same moved row once and prevents double cabling.",
  "deprecated_date": null,
  "docstatus": 0,
  "doctype": "InductOne Configuration Option",
  "effective_date": null,
  "internal_notes": "Use when the magnet lock is relocated and only the magnet-lock electrical cable needs the relocated length.",
  "is_active": 1,
  "is_default_selection": 0,
  "mapping_status": "Complete",
  "mappings_table": [
   {
    "action": "REPLACE",
    "expand_mode": "AS_ITEM_ONLY",
    "parameter_key": null,
    "parent": "DEV-COMP-MAGLOCK",
    "parentfield": "mappings_table",
    "parenttype": "InductOne Configuration Option",
    "preserve_target_item_identity": 1,
    "qty_fixed": 1.0,
    "qty_source": "FIXED",
    "replace_count": 1,
    "replace_scope": "ALL_OCCURRENCES",
    "replace_with_bom": null,
    "replace_with_item": "MDCM-8FP-10M-R  & MDC-8MP-FW11",
    "required_for_release": 1,
    "row_order": 10,
    "structural_effect_mode": "AUTO",
    "target_balloon": "159",
    "target_bom": null,
    "target_item": "WKC 8T-4-RSC 8T"
   }
  ],
  "modified": "2026-07-08 11:04:13.713249",
  "name": "DEV-COMP-MAGLOCK",
  "option_category": "Electrical",
  "option_code": "DEV-COMP-MAGLOCK",
  "option_group": "Maglock Position",
  "option_group_required": 1,
  "option_name": "Deviation — Magnet Lock Relocated",
  "owner_role": "Ops",
  "requires_ops_approval": 0,
  "sort_order": 130,
  "status": "Draft",
  "workflow_state": null
 }
]
