[
  {
    "name": "InductOne Options Catalog",
    "owner": "michael.king@plusonerobotics.com",
    "creation": "2026-04-16 14:43:58.045044",
    "modified": "2026-07-14 13:52:54.386453",
    "modified_by": "Administrator",
    "docstatus": 0,
    "idx": 0,
    "print_format_for": "DocType",
    "doc_type": "InductOne Options Catalog",
    "report": null,
    "module": "Operations - POR",
    "default_print_language": "en-US",
    "standard": "No",
    "custom_format": 1,
    "disabled": 0,
    "pdf_generator": "wkhtmltopdf",
    "print_format_type": "Jinja",
    "raw_printing": 0,
    "html": "{% set status_mode = frappe.form_dict.get('status_mode') or 'released_only' %}\r\n{% set category_raw = frappe.form_dict.get('option_category') or '' %}\r\n{% set group_raw = frappe.form_dict.get('option_group') or '' %}\r\n{% set default_only = (frappe.form_dict.get('default_only') or '0') in ['1', 'true', 'True', 'yes', 'on'] %}\r\n{% set include_builder = (frappe.form_dict.get('include_builder') or '0') in ['1', 'true', 'True', 'yes', 'on'] %}\r\n\r\n{% if status_mode == 'released_only' %}\r\n  {% set allowed_statuses = ['Released'] %}\r\n  {% set include_inactive = False %}\r\n  {% set status_label = 'Released only' %}\r\n{% elif status_mode == 'draft_only' %}\r\n  {% set allowed_statuses = ['Draft'] %}\r\n  {% set include_inactive = False %}\r\n  {% set status_label = 'Draft only' %}\r\n{% elif status_mode == 'all_active' %}\r\n  {% set allowed_statuses = ['Draft', 'Released'] %}\r\n  {% set include_inactive = False %}\r\n  {% set status_label = 'All active options' %}\r\n{% elif status_mode == 'all_including_inactive' %}\n  {% set allowed_statuses = ['Draft', 'Released', 'Deprecated'] %}\n  {% set include_inactive = True %}\r\n  {% set status_label = 'All options, including inactive' %}\r\n{% else %}\r\n  {% set allowed_statuses = ['Released'] %}\r\n  {% set include_inactive = False %}\r\n  {% set status_label = 'Released only' %}\r\n{% endif %}\r\n\r\n{% set category_filters = [] %}\r\n{% for c in category_raw.split(',') %}\r\n  {% if c | trim %}\r\n    {% set _ = category_filters.append(c | trim) %}\r\n  {% endif %}\r\n{% endfor %}\r\n\r\n{% set group_filters = [] %}\r\n{% for g in group_raw.split(',') %}\r\n  {% if g | trim %}\r\n    {% set _ = group_filters.append(g | trim) %}\r\n  {% endif %}\r\n{% endfor %}\r\n\r\n{% set all_options = frappe.get_all(\r\n    'InductOne Configuration Option',\r\n    fields=[\r\n      'name',\r\n      'option_code',\r\n      'option_name',\r\n      'option_category',\r\n      'option_group',\r\n      'option_group_required',\r\n      'is_default_selection',\r\n      'is_active',\r\n      'status',\r\n      'mapping_status',\r\n      'builder_description',\r\n      'internal_notes',\r\n      'sort_order'\r\n    ],\r\n    order_by='option_category asc, sort_order asc, option_code asc'\r\n) %}\r\n\r\n{% set filtered_options = [] %}\r\n\r\n{% for o in all_options %}\r\n  {% set active_ok = include_inactive or ((o.is_active or 0) | int == 1) %}\r\n  {% set status_ok = (allowed_statuses | length == 0) or (o.status in allowed_statuses) %}\r\n  {% set category_ok = (category_filters | length == 0) or (o.option_category in category_filters) %}\r\n  {% set group_ok = (group_filters | length == 0) or (o.option_group in group_filters) %}\r\n  {% set default_ok = (not default_only) or ((o.is_default_selection or 0) | int == 1) %}\r\n\r\n  {% if active_ok and status_ok and category_ok and group_ok and default_ok %}\r\n    {% set _ = filtered_options.append(o) %}\r\n  {% endif %}\r\n{% endfor %}\r\n\r\n{% set categories = [] %}\r\n\r\n{% for o in filtered_options %}\r\n  {% if o.option_category not in categories %}\r\n    {% set _ = categories.append(o.option_category) %}\r\n  {% endif %}\r\n{% endfor %}\r\n\r\n{% set total_count = filtered_options | length %}\r\n{% set released_count = filtered_options | selectattr('status', 'equalto', 'Released') | list | length %}\r\n{% set draft_count = filtered_options | selectattr('status', 'equalto', 'Draft') | list | length %}\r\n\r\n{% set filter_summary = [] %}\r\n{% set _ = filter_summary.append('Status: ' ~ status_label) %}\r\n\r\n{% if category_filters | length %}\r\n  {% set _ = filter_summary.append('Category: ' ~ (category_filters | join(', '))) %}\r\n{% endif %}\r\n\r\n{% if group_filters | length %}\r\n  {% set _ = filter_summary.append('Group: ' ~ (group_filters | join(', '))) %}\r\n{% endif %}\r\n\r\n{% if default_only %}\r\n  {% set _ = filter_summary.append('Default selections only') %}\r\n{% endif %}\r\n\r\n<div class=\"catalog-header\">\r\n  <div class=\"catalog-title\">InductOne Configuration Options Catalog</div>\r\n\r\n  {% if include_builder %}\r\n    <div class=\"catalog-subtitle\">Comprehensive Internal Version \u2014 Sales + Engineering Descriptions</div>\r\n  {% else %}\r\n    <div class=\"catalog-subtitle\">Sales-Facing Version \u2014 Available Released Options</div>\r\n  {% endif %}\r\n\r\n  <div class=\"catalog-meta\">\r\n    Generated {{ frappe.utils.now_datetime().strftime('%B %d, %Y') }}\r\n    &nbsp;|&nbsp; {{ filter_summary | join(' | ') }}\r\n    {% if include_builder %}\r\n      &nbsp;|&nbsp; Confidential Internal Use\r\n    {% else %}\r\n      &nbsp;|&nbsp; Confidential\r\n    {% endif %}\r\n  </div>\r\n</div>\r\n\r\n<div class=\"summary-bar\">\r\n  <div class=\"summary-item\">\r\n    <span class=\"summary-label\">Filtered Options</span>\r\n    <span class=\"summary-value\">{{ total_count }}</span>\r\n  </div>\r\n\r\n  <div class=\"summary-item\">\r\n    <span class=\"summary-label\">Released</span>\r\n    <span class=\"summary-value\">{{ released_count }}</span>\r\n  </div>\r\n\r\n  <div class=\"summary-item\">\r\n    <span class=\"summary-label\">Draft</span>\r\n    <span class=\"summary-value\">{{ draft_count }}</span>\r\n  </div>\r\n\r\n  <div class=\"summary-item\">\r\n    <span class=\"summary-label\">Categories</span>\r\n    <span class=\"summary-value\">{{ categories | length }}</span>\r\n  </div>\r\n</div>\r\n\r\n{% for category in categories | sort %}\r\n{% set cat_options = filtered_options | selectattr('option_category', 'equalto', category) | list %}\r\n\r\n{% if cat_options %}\r\n<div class=\"category-block\">\r\n\r\n  {% for o in cat_options %}\r\n    {% if loop.first %}\r\n    <div class=\"category-start-keep\">\r\n      <div class=\"category-heading\">{{ category or 'Uncategorized' }} &nbsp;({{ cat_options | length }})</div>\r\n    {% endif %}\r\n\r\n    <div class=\"option-card\">\r\n      <div class=\"option-card-header\">\r\n        <span class=\"option-code\">{{ o.option_code or '\u2014' }}</span>\r\n\r\n        <span class=\"option-name\">\r\n          {{ o.option_name or '\u2014' }}\r\n\r\n          {% if o.option_group %}\r\n            <span class=\"option-group-tag\">{{ o.option_group }}</span>\r\n          {% endif %}\r\n        </span>\r\n\r\n        <span class=\"option-status {% if o.status == 'Released' %}released{% elif o.status == 'Draft' %}draft{% endif %}\">\r\n          {{ o.status or '' }}\r\n        </span>\r\n      </div>\r\n\r\n      {% set sales_desc = o.internal_notes or '' %}\r\n      {% set builder_desc = o.builder_description or '' %}\r\n\r\n      {% if sales_desc %}\r\n      <div class=\"description-block sales-description\">\r\n        <div class=\"description-label\">Sales Description</div>\r\n        <div class=\"option-description\">\r\n          {{ sales_desc | trim | replace('\\n', '<br>') }}\r\n        </div>\r\n      </div>\r\n      {% endif %}\r\n\r\n      {% if include_builder and builder_desc %}\r\n        {% set _eff = builder_desc.split('Configuration effect:') %}\r\n\r\n        <div class=\"description-block builder-description\">\r\n          <div class=\"description-label\">Engineering / Builder Description</div>\r\n\r\n          <div class=\"builder-main-description\">\r\n            {{ _eff[0] | trim | replace('\\n', '<br>') }}\r\n          </div>\r\n\r\n          {% if _eff | length > 1 %}\r\n            {% set _notes = _eff[1].split('Notes:') %}\r\n\r\n            <div class=\"builder-subsection configuration-effect\">\r\n              <div class=\"builder-subsection-label\">Configuration Effect</div>\r\n              <div class=\"builder-subsection-body\">\r\n                {{ _notes[0] | trim | replace('\\n', '<br>') }}\r\n              </div>\r\n            </div>\r\n\r\n            {% if _notes | length > 1 %}\r\n            <div class=\"builder-subsection builder-notes\">\r\n              <div class=\"builder-subsection-label\">Notes</div>\r\n              <div class=\"builder-subsection-body\">\r\n                {{ _notes[1] | trim | replace('\\n', '<br>') }}\r\n              </div>\r\n            </div>\r\n            {% endif %}\r\n          {% endif %}\r\n        </div>\r\n      {% endif %}\r\n\r\n      {% if not sales_desc and (not include_builder or not builder_desc) %}\r\n      <div class=\"option-description-empty\">No description available.</div>\r\n      {% endif %}\r\n    </div>\r\n\r\n    {% if loop.first %}\r\n    </div>\r\n    {% endif %}\r\n  {% endfor %}\r\n\r\n</div>\r\n{% endif %}\r\n{% endfor %}\r\n\r\n{% if total_count == 0 %}\r\n<p class=\"no-options\">\r\n  No options matched the selected catalog filters:\r\n  {{ filter_summary | join(' | ') }}\r\n</p>\r\n{% endif %}\r\n\r\n<div class=\"footer-block\">\r\n  <span>Plus One Robotics \u2014 Confidential and Proprietary</span>\r\n\r\n  {% if include_builder %}\r\n    <span>InductOne Options Catalog, Comprehensive Internal Version &nbsp;|&nbsp; {{ frappe.utils.now_datetime().strftime('%Y-%m-%d') }}</span>\r\n  {% else %}\r\n    <span>InductOne Options Catalog &nbsp;|&nbsp; {{ frappe.utils.now_datetime().strftime('%Y-%m-%d') }}</span>\r\n  {% endif %}\r\n</div>",
    "raw_commands": null,
    "margin_top": 15.0,
    "margin_bottom": 15.0,
    "margin_left": 15.0,
    "margin_right": 15.0,
    "align_labels_right": 0,
    "show_section_headings": 0,
    "line_breaks": 0,
    "absolute_value": 0,
    "font_size": 14,
    "font": "Inter",
    "page_number": "Bottom Center",
    "css": ".catalog-header {\r\n  border-bottom: 2px solid #111;\r\n  padding-bottom: 12px;\r\n  margin-bottom: 14px;\r\n}\r\n\r\n.catalog-title {\r\n  font-size: 22px;\r\n  font-weight: 700;\r\n  color: #111;\r\n}\r\n\r\n.catalog-subtitle {\r\n  font-size: 13px;\r\n  margin-top: 4px;\r\n  color: #444;\r\n}\r\n\r\n.catalog-meta {\r\n  font-size: 10px;\r\n  margin-top: 6px;\r\n  color: #666;\r\n}\r\n\r\n.summary-bar {\r\n  display: table;\r\n  width: 100%;\r\n  border: 1px solid #d9d9d9;\r\n  margin-bottom: 18px;\r\n}\r\n\r\n.summary-item {\r\n  display: table-cell;\r\n  width: 25%;\r\n  padding: 8px 10px;\r\n  border-right: 1px solid #d9d9d9;\r\n  vertical-align: middle;\r\n}\r\n\r\n.summary-item:last-child {\r\n  border-right: none;\r\n}\r\n\r\n.summary-label {\r\n  display: block;\r\n  font-size: 9px;\r\n  text-transform: uppercase;\r\n  color: #666;\r\n  letter-spacing: 0.5px;\r\n}\r\n\r\n.summary-value {\r\n  display: block;\r\n  font-size: 15px;\r\n  font-weight: 700;\r\n  color: #111;\r\n  margin-top: 2px;\r\n}\r\n\r\n.category-block {\r\n  margin-bottom: 20px;\r\n}\r\n\r\n.category-start-keep {\r\n  page-break-inside: avoid;\r\n  break-inside: avoid;\r\n}\r\n\r\n.category-heading {\r\n  background: #111;\r\n  color: #fff;\r\n  padding: 7px 10px;\r\n  font-size: 12px;\r\n  font-weight: 700;\r\n  letter-spacing: 1px;\r\n  text-transform: uppercase;\r\n  border-radius: 3px;\r\n  margin-bottom: 8px;\r\n  page-break-after: avoid;\r\n  break-after: avoid;\r\n}\r\n\r\n.option-card {\r\n  border: 1px solid #d6d6d6;\r\n  border-radius: 4px;\r\n  margin-bottom: 10px;\r\n  page-break-inside: avoid;\r\n  break-inside: avoid;\r\n  overflow: hidden;\r\n}\r\n\r\n.option-card-header {\r\n  background: #f2f2f2;\r\n  border-bottom: 1px solid #d6d6d6;\r\n  padding: 8px 10px;\r\n  font-size: 10px;\r\n}\r\n\r\n.option-code {\r\n  font-weight: 700;\r\n  color: #111;\r\n  margin-right: 8px;\r\n}\r\n\r\n.option-name {\r\n  font-weight: 600;\r\n  color: #222;\r\n}\r\n\r\n.option-group-tag {\r\n  font-size: 8px;\r\n  color: #2f45d8;\r\n  margin-left: 8px;\r\n  text-transform: uppercase;\r\n}\r\n\r\n.option-status {\r\n  float: right;\r\n  font-size: 8px;\r\n  font-weight: 700;\r\n  text-transform: uppercase;\r\n}\r\n\r\n.option-status.released {\r\n  color: #1f7a35;\r\n}\r\n\r\n.option-status.draft {\r\n  color: #a36b00;\r\n}\r\n\r\n.description-block {\r\n  padding: 9px 12px;\r\n  border-bottom: 1px solid #ededed;\r\n}\r\n\r\n.description-block:last-child {\r\n  border-bottom: none;\r\n}\r\n\r\n.description-label {\r\n  font-size: 8px;\r\n  font-weight: 700;\r\n  text-transform: uppercase;\r\n  letter-spacing: 0.7px;\r\n  margin-bottom: 5px;\r\n}\r\n\r\n.sales-description {\r\n  background: #fbfdff;\r\n}\r\n\r\n.sales-description .description-label {\r\n  color: #005eb8;\r\n}\r\n\r\n.builder-description {\r\n  background: #fffaf2;\r\n}\r\n\r\n.builder-description .description-label {\r\n  color: #6b3f00;\r\n}\r\n\r\n.option-description {\r\n  font-size: 10px;\r\n  line-height: 1.45;\r\n  color: #111;\r\n}\r\n\r\n.builder-main-description {\r\n  font-size: 10px;\r\n  line-height: 1.55;\r\n  color: #344054;\r\n  margin-bottom: 12px;\r\n  padding-bottom: 12px;\r\n  border-bottom: 1px solid #f2f4f7;\r\n}\r\n\r\n.builder-subsection {\r\n  margin-top: 10px;\r\n}\r\n\r\n.builder-subsection-label {\r\n  font-size: 8.5px;\r\n  font-weight: 700;\r\n  text-transform: uppercase;\r\n  letter-spacing: 1px;\r\n  color: #1794CE;\r\n  margin-bottom: 5px;\r\n}\r\n\r\n.builder-subsection-body {\r\n  font-size: 10px;\r\n  color: #475467;\r\n  line-height: 1.6;\r\n  padding-left: 12px;\r\n  border-left: 2px solid #1794CE;\r\n}\r\n\r\n.builder-notes .builder-subsection-body {\r\n  border-left-color: #D0D5DD;\r\n}\r\n\r\n.option-description-empty {\r\n  padding: 10px 12px;\r\n  font-size: 10px;\r\n  color: #999;\r\n  font-style: italic;\r\n}\r\n\r\n.no-options {\r\n  font-size: 12px;\r\n  color: #777;\r\n  padding: 12px;\r\n  background: #f9fafb;\r\n  border: 1px solid #eaecf0;\r\n  border-radius: 4px;\r\n}\r\n\r\n.footer-block {\r\n  margin-top: 24px;\r\n  border-top: 1px solid #ccc;\r\n  padding-top: 8px;\r\n  font-size: 9px;\r\n  color: #666;\r\n  display: flex;\r\n  justify-content: space-between;\r\n}\r\n\r\n@media print {\r\n  .category-heading,\r\n  .option-card-header,\r\n  .sales-description,\r\n  .builder-description {\r\n    -webkit-print-color-adjust: exact;\r\n    print-color-adjust: exact;\r\n  }\r\n}",
    "format_data": null,
    "print_format_builder": 0,
    "print_format_builder_beta": 0,
    "doctype": "Print Format"
  },
  {
    "name": "InductOne Options Catalog - Comprehensive",
    "owner": "michael.king@plusonerobotics.com",
    "creation": "2026-06-11 11:19:14.239353",
    "modified": "2026-07-14 13:52:54.814995",
    "modified_by": "Administrator",
    "docstatus": 0,
    "idx": 0,
    "print_format_for": "DocType",
    "doc_type": "InductOne Options Catalog",
    "report": null,
    "module": "Operations - POR",
    "default_print_language": "en-US",
    "standard": "No",
    "custom_format": 1,
    "disabled": 0,
    "pdf_generator": "wkhtmltopdf",
    "print_format_type": "Jinja",
    "raw_printing": 0,
    "html": "{% set status_mode = frappe.form_dict.get('status_mode') or 'released_only' %}\r\n{% set category_raw = frappe.form_dict.get('option_category') or '' %}\r\n{% set group_raw = frappe.form_dict.get('option_group') or '' %}\r\n{% set default_only = (frappe.form_dict.get('default_only') or '0') in ['1', 'true', 'True', 'yes', 'on'] %}\r\n{% set include_builder = (frappe.form_dict.get('include_builder') or '0') in ['1', 'true', 'True', 'yes', 'on'] %}\r\n\r\n{% if status_mode == 'released_only' %}\r\n  {% set allowed_statuses = ['Released'] %}\r\n  {% set include_inactive = False %}\r\n  {% set status_label = 'Released only' %}\r\n{% elif status_mode == 'draft_only' %}\r\n  {% set allowed_statuses = ['Draft'] %}\r\n  {% set include_inactive = False %}\r\n  {% set status_label = 'Draft only' %}\r\n{% elif status_mode == 'all_active' %}\r\n  {% set allowed_statuses = ['Draft', 'Released'] %}\r\n  {% set include_inactive = False %}\r\n  {% set status_label = 'All active options' %}\r\n{% elif status_mode == 'all_including_inactive' %}\n  {% set allowed_statuses = ['Draft', 'Released', 'Deprecated'] %}\n  {% set include_inactive = True %}\r\n  {% set status_label = 'All options, including inactive' %}\r\n{% else %}\r\n  {% set allowed_statuses = ['Released'] %}\r\n  {% set include_inactive = False %}\r\n  {% set status_label = 'Released only' %}\r\n{% endif %}\r\n\r\n{% set category_filters = [] %}\r\n{% for c in category_raw.split(',') %}\r\n  {% if c | trim %}\r\n    {% set _ = category_filters.append(c | trim) %}\r\n  {% endif %}\r\n{% endfor %}\r\n\r\n{% set group_filters = [] %}\r\n{% for g in group_raw.split(',') %}\r\n  {% if g | trim %}\r\n    {% set _ = group_filters.append(g | trim) %}\r\n  {% endif %}\r\n{% endfor %}\r\n\r\n{% set all_options = frappe.get_all(\r\n    'InductOne Configuration Option',\r\n    fields=[\r\n      'name',\r\n      'option_code',\r\n      'option_name',\r\n      'option_category',\r\n      'option_group',\r\n      'option_group_required',\r\n      'is_default_selection',\r\n      'is_active',\r\n      'status',\r\n      'mapping_status',\r\n      'builder_description',\r\n      'internal_notes',\r\n      'sort_order'\r\n    ],\r\n    order_by='option_category asc, sort_order asc, option_code asc'\r\n) %}\r\n\r\n{% set filtered_options = [] %}\r\n\r\n{% for o in all_options %}\r\n  {% set active_ok = include_inactive or ((o.is_active or 0) | int == 1) %}\r\n  {% set status_ok = (allowed_statuses | length == 0) or (o.status in allowed_statuses) %}\r\n  {% set category_ok = (category_filters | length == 0) or (o.option_category in category_filters) %}\r\n  {% set group_ok = (group_filters | length == 0) or (o.option_group in group_filters) %}\r\n  {% set default_ok = (not default_only) or ((o.is_default_selection or 0) | int == 1) %}\r\n\r\n  {% if active_ok and status_ok and category_ok and group_ok and default_ok %}\r\n    {% set _ = filtered_options.append(o) %}\r\n  {% endif %}\r\n{% endfor %}\r\n\r\n{% set categories = [] %}\r\n\r\n{% for o in filtered_options %}\r\n  {% if o.option_category not in categories %}\r\n    {% set _ = categories.append(o.option_category) %}\r\n  {% endif %}\r\n{% endfor %}\r\n\r\n{% set total_count = filtered_options | length %}\r\n{% set released_count = filtered_options | selectattr('status', 'equalto', 'Released') | list | length %}\r\n{% set draft_count = filtered_options | selectattr('status', 'equalto', 'Draft') | list | length %}\r\n\r\n{% set filter_summary = [] %}\r\n{% set _ = filter_summary.append('Status: ' ~ status_label) %}\r\n\r\n{% if category_filters | length %}\r\n  {% set _ = filter_summary.append('Category: ' ~ (category_filters | join(', '))) %}\r\n{% endif %}\r\n\r\n{% if group_filters | length %}\r\n  {% set _ = filter_summary.append('Group: ' ~ (group_filters | join(', '))) %}\r\n{% endif %}\r\n\r\n{% if default_only %}\r\n  {% set _ = filter_summary.append('Default selections only') %}\r\n{% endif %}\r\n\r\n<div class=\"catalog-header\">\r\n  <div class=\"catalog-title\">InductOne Configuration Options Catalog</div>\r\n\r\n  {% if include_builder %}\r\n    <div class=\"catalog-subtitle\">Comprehensive Internal Version \u2014 Sales + Engineering Descriptions</div>\r\n  {% else %}\r\n    <div class=\"catalog-subtitle\">Sales-Facing Version \u2014 Available Released Options</div>\r\n  {% endif %}\r\n\r\n  <div class=\"catalog-meta\">\r\n    Generated {{ frappe.utils.now_datetime().strftime('%B %d, %Y') }}\r\n    &nbsp;|&nbsp; {{ filter_summary | join(' | ') }}\r\n    {% if include_builder %}\r\n      &nbsp;|&nbsp; Confidential Internal Use\r\n    {% else %}\r\n      &nbsp;|&nbsp; Confidential\r\n    {% endif %}\r\n  </div>\r\n</div>\r\n\r\n<div class=\"summary-bar\">\r\n  <div class=\"summary-item\">\r\n    <span class=\"summary-label\">Filtered Options</span>\r\n    <span class=\"summary-value\">{{ total_count }}</span>\r\n  </div>\r\n\r\n  <div class=\"summary-item\">\r\n    <span class=\"summary-label\">Released</span>\r\n    <span class=\"summary-value\">{{ released_count }}</span>\r\n  </div>\r\n\r\n  <div class=\"summary-item\">\r\n    <span class=\"summary-label\">Draft</span>\r\n    <span class=\"summary-value\">{{ draft_count }}</span>\r\n  </div>\r\n\r\n  <div class=\"summary-item\">\r\n    <span class=\"summary-label\">Categories</span>\r\n    <span class=\"summary-value\">{{ categories | length }}</span>\r\n  </div>\r\n</div>\r\n\r\n{% for category in categories | sort %}\r\n{% set cat_options = filtered_options | selectattr('option_category', 'equalto', category) | list %}\r\n\r\n{% if cat_options %}\r\n<div class=\"category-block\">\r\n\r\n  {% for o in cat_options %}\r\n    {% if loop.first %}\r\n    <div class=\"category-start-keep\">\r\n      <div class=\"category-heading\">{{ category or 'Uncategorized' }} &nbsp;({{ cat_options | length }})</div>\r\n    {% endif %}\r\n\r\n    <div class=\"option-card\">\r\n      <div class=\"option-card-header\">\r\n        <span class=\"option-code\">{{ o.option_code or '\u2014' }}</span>\r\n\r\n        <span class=\"option-name\">\r\n          {{ o.option_name or '\u2014' }}\r\n\r\n          {% if o.option_group %}\r\n            <span class=\"option-group-tag\">{{ o.option_group }}</span>\r\n          {% endif %}\r\n        </span>\r\n\r\n        <span class=\"option-status {% if o.status == 'Released' %}released{% elif o.status == 'Draft' %}draft{% endif %}\">\r\n          {{ o.status or '' }}\r\n        </span>\r\n      </div>\r\n\r\n      {% set sales_desc = o.internal_notes or '' %}\r\n      {% set builder_desc = o.builder_description or '' %}\r\n\r\n      {% if sales_desc %}\r\n      <div class=\"description-block sales-description\">\r\n        <div class=\"description-label\">Sales Description</div>\r\n        <div class=\"option-description\">\r\n          {{ sales_desc | trim | replace('\\n', '<br>') }}\r\n        </div>\r\n      </div>\r\n      {% endif %}\r\n\r\n      {% if include_builder and builder_desc %}\r\n        {% set _eff = builder_desc.split('Configuration effect:') %}\r\n\r\n        <div class=\"description-block builder-description\">\r\n          <div class=\"description-label\">Engineering / Builder Description</div>\r\n\r\n          <div class=\"builder-main-description\">\r\n            {{ _eff[0] | trim | replace('\\n', '<br>') }}\r\n          </div>\r\n\r\n          {% if _eff | length > 1 %}\r\n            {% set _notes = _eff[1].split('Notes:') %}\r\n\r\n            <div class=\"builder-subsection configuration-effect\">\r\n              <div class=\"builder-subsection-label\">Configuration Effect</div>\r\n              <div class=\"builder-subsection-body\">\r\n                {{ _notes[0] | trim | replace('\\n', '<br>') }}\r\n              </div>\r\n            </div>\r\n\r\n            {% if _notes | length > 1 %}\r\n            <div class=\"builder-subsection builder-notes\">\r\n              <div class=\"builder-subsection-label\">Notes</div>\r\n              <div class=\"builder-subsection-body\">\r\n                {{ _notes[1] | trim | replace('\\n', '<br>') }}\r\n              </div>\r\n            </div>\r\n            {% endif %}\r\n          {% endif %}\r\n        </div>\r\n      {% endif %}\r\n\r\n      {% if not sales_desc and (not include_builder or not builder_desc) %}\r\n      <div class=\"option-description-empty\">No description available.</div>\r\n      {% endif %}\r\n    </div>\r\n\r\n    {% if loop.first %}\r\n    </div>\r\n    {% endif %}\r\n  {% endfor %}\r\n\r\n</div>\r\n{% endif %}\r\n{% endfor %}\r\n\r\n{% if total_count == 0 %}\r\n<p class=\"no-options\">\r\n  No options matched the selected catalog filters:\r\n  {{ filter_summary | join(' | ') }}\r\n</p>\r\n{% endif %}\r\n\r\n<div class=\"footer-block\">\r\n  <span>Plus One Robotics \u2014 Confidential and Proprietary</span>\r\n\r\n  {% if include_builder %}\r\n    <span>InductOne Options Catalog, Comprehensive Internal Version &nbsp;|&nbsp; {{ frappe.utils.now_datetime().strftime('%Y-%m-%d') }}</span>\r\n  {% else %}\r\n    <span>InductOne Options Catalog &nbsp;|&nbsp; {{ frappe.utils.now_datetime().strftime('%Y-%m-%d') }}</span>\r\n  {% endif %}\r\n</div>",
    "raw_commands": null,
    "margin_top": 15.0,
    "margin_bottom": 15.0,
    "margin_left": 15.0,
    "margin_right": 15.0,
    "align_labels_right": 0,
    "show_section_headings": 0,
    "line_breaks": 0,
    "absolute_value": 0,
    "font_size": 14,
    "font": null,
    "page_number": "Hide",
    "css": ".catalog-header {\r\n  border-bottom: 2px solid #111;\r\n  padding-bottom: 12px;\r\n  margin-bottom: 14px;\r\n}\r\n\r\n.catalog-title {\r\n  font-size: 22px;\r\n  font-weight: 700;\r\n  color: #111;\r\n}\r\n\r\n.catalog-subtitle {\r\n  font-size: 13px;\r\n  margin-top: 4px;\r\n  color: #444;\r\n}\r\n\r\n.catalog-meta {\r\n  font-size: 10px;\r\n  margin-top: 6px;\r\n  color: #666;\r\n}\r\n\r\n.summary-bar {\r\n  display: table;\r\n  width: 100%;\r\n  border: 1px solid #d9d9d9;\r\n  margin-bottom: 18px;\r\n}\r\n\r\n.summary-item {\r\n  display: table-cell;\r\n  width: 25%;\r\n  padding: 8px 10px;\r\n  border-right: 1px solid #d9d9d9;\r\n  vertical-align: middle;\r\n}\r\n\r\n.summary-item:last-child {\r\n  border-right: none;\r\n}\r\n\r\n.summary-label {\r\n  display: block;\r\n  font-size: 9px;\r\n  text-transform: uppercase;\r\n  color: #666;\r\n  letter-spacing: 0.5px;\r\n}\r\n\r\n.summary-value {\r\n  display: block;\r\n  font-size: 15px;\r\n  font-weight: 700;\r\n  color: #111;\r\n  margin-top: 2px;\r\n}\r\n\r\n.category-block {\r\n  margin-bottom: 20px;\r\n}\r\n\r\n.category-start-keep {\r\n  page-break-inside: avoid;\r\n  break-inside: avoid;\r\n}\r\n\r\n.category-heading {\r\n  background: #111;\r\n  color: #fff;\r\n  padding: 7px 10px;\r\n  font-size: 12px;\r\n  font-weight: 700;\r\n  letter-spacing: 1px;\r\n  text-transform: uppercase;\r\n  border-radius: 3px;\r\n  margin-bottom: 8px;\r\n  page-break-after: avoid;\r\n  break-after: avoid;\r\n}\r\n\r\n.option-card {\r\n  border: 1px solid #d6d6d6;\r\n  border-radius: 4px;\r\n  margin-bottom: 10px;\r\n  page-break-inside: avoid;\r\n  break-inside: avoid;\r\n  overflow: hidden;\r\n}\r\n\r\n.option-card-header {\r\n  background: #f2f2f2;\r\n  border-bottom: 1px solid #d6d6d6;\r\n  padding: 8px 10px;\r\n  font-size: 10px;\r\n}\r\n\r\n.option-code {\r\n  font-weight: 700;\r\n  color: #111;\r\n  margin-right: 8px;\r\n}\r\n\r\n.option-name {\r\n  font-weight: 600;\r\n  color: #222;\r\n}\r\n\r\n.option-group-tag {\r\n  font-size: 8px;\r\n  color: #2f45d8;\r\n  margin-left: 8px;\r\n  text-transform: uppercase;\r\n}\r\n\r\n.option-status {\r\n  float: right;\r\n  font-size: 8px;\r\n  font-weight: 700;\r\n  text-transform: uppercase;\r\n}\r\n\r\n.option-status.released {\r\n  color: #1f7a35;\r\n}\r\n\r\n.option-status.draft {\r\n  color: #a36b00;\r\n}\r\n\r\n.description-block {\r\n  padding: 9px 12px;\r\n  border-bottom: 1px solid #ededed;\r\n}\r\n\r\n.description-block:last-child {\r\n  border-bottom: none;\r\n}\r\n\r\n.description-label {\r\n  font-size: 8px;\r\n  font-weight: 700;\r\n  text-transform: uppercase;\r\n  letter-spacing: 0.7px;\r\n  margin-bottom: 5px;\r\n}\r\n\r\n.sales-description {\r\n  background: #fbfdff;\r\n}\r\n\r\n.sales-description .description-label {\r\n  color: #005eb8;\r\n}\r\n\r\n.builder-description {\r\n  background: #fffaf2;\r\n}\r\n\r\n.builder-description .description-label {\r\n  color: #6b3f00;\r\n}\r\n\r\n.option-description {\r\n  font-size: 10px;\r\n  line-height: 1.45;\r\n  color: #111;\r\n}\r\n\r\n.builder-main-description {\r\n  font-size: 10px;\r\n  line-height: 1.55;\r\n  color: #344054;\r\n  margin-bottom: 12px;\r\n  padding-bottom: 12px;\r\n  border-bottom: 1px solid #f2f4f7;\r\n}\r\n\r\n.builder-subsection {\r\n  margin-top: 10px;\r\n}\r\n\r\n.builder-subsection-label {\r\n  font-size: 8.5px;\r\n  font-weight: 700;\r\n  text-transform: uppercase;\r\n  letter-spacing: 1px;\r\n  color: #1794CE;\r\n  margin-bottom: 5px;\r\n}\r\n\r\n.builder-subsection-body {\r\n  font-size: 10px;\r\n  color: #475467;\r\n  line-height: 1.6;\r\n  padding-left: 12px;\r\n  border-left: 2px solid #1794CE;\r\n}\r\n\r\n.builder-notes .builder-subsection-body {\r\n  border-left-color: #D0D5DD;\r\n}\r\n\r\n.option-description-empty {\r\n  padding: 10px 12px;\r\n  font-size: 10px;\r\n  color: #999;\r\n  font-style: italic;\r\n}\r\n\r\n.no-options {\r\n  font-size: 12px;\r\n  color: #777;\r\n  padding: 12px;\r\n  background: #f9fafb;\r\n  border: 1px solid #eaecf0;\r\n  border-radius: 4px;\r\n}\r\n\r\n.footer-block {\r\n  margin-top: 24px;\r\n  border-top: 1px solid #ccc;\r\n  padding-top: 8px;\r\n  font-size: 9px;\r\n  color: #666;\r\n  display: flex;\r\n  justify-content: space-between;\r\n}\r\n\r\n@media print {\r\n  .category-heading,\r\n  .option-card-header,\r\n  .sales-description,\r\n  .builder-description {\r\n    -webkit-print-color-adjust: exact;\r\n    print-color-adjust: exact;\r\n  }\r\n}",
    "format_data": null,
    "print_format_builder": 0,
    "print_format_builder_beta": 0,
    "doctype": "Print Format"
  }
]